helpers/example_model.py
mitts-0.0.2.dist-info/METADATA
mitts-0.0.2.dist-info/WHEEL
mitts-0.0.2.dist-info/top_level.txt
mitts-0.0.2.dist-info/RECORD
