Metadata-Version: 2.1
Name: mitts
Version: 0.0.2
Summary: Don't get burned with common torch training errors
Author-email: Jake Williams <jakew@duck.com>
Project-URL: Homepage, https://jakemwilliams.com
Project-URL: Repository, https://github.com/JakeWilliams22/mitts
Classifier: License :: OSI Approved :: MIT License
Classifier: Programming Language :: Python
Classifier: Programming Language :: Python :: 3
Requires-Python: >=3.6
Requires-Dist: torch
Provides-Extra: dev
Requires-Dist: pytest ; extra == 'dev'
